prepare_toolbox/__init__.py
prepare_toolbox/command.py
prepare_toolbox/core.py
prepare_toolbox/file.py
prepare_toolbox/py.typed
prepare_toolbox/utils.py
prepare_toolbox/zip.py
prepare_toolbox-0.4.0.dist-info/LICENSE
prepare_toolbox-0.4.0.dist-info/METADATA
prepare_toolbox-0.4.0.dist-info/WHEEL
prepare_toolbox-0.4.0.dist-info/RECORD
