Metadata-Version: 2.1
Name: prepare-toolbox
Version: 0.4.0
Summary: Toolbox containing helper functions for prepare-assignment actions
License: MIT
Author: Bonajo
Author-email: m.bonajo@fontys.nl
Requires-Python: >=3.8,<4.0
Classifier: License :: OSI Approved :: MIT License
Classifier: Programming Language :: Python :: 3
Classifier: Programming Language :: Python :: 3.8
Classifier: Programming Language :: Python :: 3.9
Classifier: Programming Language :: Python :: 3.10
Classifier: Programming Language :: Python :: 3.11
Requires-Dist: braceexpand (>=0.1.7,<0.2.0)
